{
    "0": {},
    "1": {
        "n": "Undersea",
        "on": true,
        "bri": 118,
        "transition": 7,
        "mainseg": 0,
        "seg": [
            {
                "id": 0,
                "start": 0,
                "stop": 120,
                "grp": 1,
                "spc": 0,
                "of": 0,
                "on": true,
                "frz": false,
                "bri": 255,
                "cct": 127,
                "col": [
                    [
                        255,
                        160,
                        0
                    ],
                    [
                        0,
                        0,
                        0
                    ],
                    [
                        0,
                        0,
                        0
                    ]
                ],
                "fx": 67,
                "sx": 29,
                "ix": 67,
                "pal": 9,
                "sel": true,
                "rev": false,
                "mi": false
            },
            {
                "stop": 0
            },
            {
                "stop": 0
            },
            {
                "stop": 0
            },
            {
                "stop": 0
            },
            {
                "stop": 0
            },
            {
                "stop": 0
            },
            {
                "stop": 0
            },
            {
                "stop": 0
            },
            {
                "stop": 0
            },
            {
                "stop": 0
            },
            {
                "stop": 0
            },
            {
                "stop": 0
            },
            {
                "stop": 0
            },
            {
                "stop": 0
            },
            {
                "stop": 0
            },
            {
                "stop": 0
            },
            {
                "stop": 0
            },
            {
                "stop": 0
            },
            {
                "stop": 0
            },
            {
                "stop": 0
            },
            {
                "stop": 0
            },
            {
                "stop": 0
            },
            {
                "stop": 0
            },
            {
                "stop": 0
            },
            {
                "stop": 0
            },
            {
                "stop": 0
            },
            {
                "stop": 0
            },
            {
                "stop": 0
            },
            {
                "stop": 0
            },
            {
                "stop": 0
            },
            {
                "stop": 0
            }
        ]
    }
}
